reyflask/__init__.py
reytool/__init__.py
reytool/rbasic.py
reytool/rcommon.py
reytool/rcompress.py
reytool/rdata.py
reytool/rdatabase.py
reytool/rdatetime.py
reytool/remail.py
reytool/rmultitask.py
reytool/roption.py
reytool/rregular.py
reytool/rrequest.py
reytool/rtext.py
reytool/rwrap.py
reyflask-0.2.dist-info/METADATA
reyflask-0.2.dist-info/WHEEL
reyflask-0.2.dist-info/top_level.txt
reyflask-0.2.dist-info/RECORD
