Metadata-Version: 2.1
Name: reyflask
Version: 0.2
Summary: Rey's personal flask set
Home-page: https://pypi.org/project/reyflask/
Author: Rey
Author-email: reyxbo@163.com
